timelogger/__init__.py
timelogger/timer.py
timelogger-0.0.3.dist-info/DESCRIPTION.rst
timelogger-0.0.3.dist-info/METADATA
timelogger-0.0.3.dist-info/RECORD
timelogger-0.0.3.dist-info/WHEEL
timelogger-0.0.3.dist-info/metadata.json
timelogger-0.0.3.dist-info/top_level.txt
