Metadata-Version: 2.0
Name: timelogger
Version: 0.0.3
Summary: A time logger for Python programs
Home-page: https://github.com/brandonmpace/timelogger
Author: Brandon M. Pace
Author-email: brandonmpace@gmail.com
License: GNU Lesser General Public License v3 or later
Keywords: debug time logging logger log stopwatch timer
Platform: any
Classifier: Development Status :: 4 - Beta
Classifier: License :: OSI Approved :: GNU Lesser General Public License v3 or later (LGPLv3+)
Classifier: Operating System :: OS Independent
Classifier: Programming Language :: Python :: 3
Requires-Python: >=3.6.5
